typen/__init__.py
typen/_decorators.py
typen/_enforcer.py
typen/exceptions.py
typen/tests/__init__.py
typen/tests/test_decorators.py
typen/tests/test_enforcer.py
typen/tests/test_package_imports.py
typen-0.0.3.dist-info/LICENSE
typen-0.0.3.dist-info/METADATA
typen-0.0.3.dist-info/WHEEL
typen-0.0.3.dist-info/top_level.txt
typen-0.0.3.dist-info/RECORD
