Metadata-Version: 2.1
Name: typen
Version: 0.0.3
Summary: Strong type hints with Traits
Home-page: https://github.com/k2bd/typen
Author: Kevin Duff
Author-email: kduff@enthought.com
License: MIT
Platform: UNKNOWN
Classifier: Programming Language :: Python :: 3
Classifier: License :: OSI Approved :: MIT License
Classifier: Operating System :: OS Independent
Classifier: Development Status :: 3 - Alpha
Classifier: Intended Audience :: Developers
Classifier: Topic :: Software Development
Requires-Python: >=3.6
Requires-Dist: traits
